{
  "version": 1,
  "skills": {
    "searxng": {
      "version": "1.0.3",
      "installedAt": 1772248540804
    },
    "skill-vetter": {
      "version": "1.0.0",
      "installedAt": 1773037321430
    },
    "tavily-search": {
      "version": "1.0.0",
      "installedAt": 1773037331090
    },
    "github": {
      "version": "1.0.0",
      "installedAt": 1773037731612
    },
    "gog": {
      "version": "1.0.0",
      "installedAt": 1773037734669
    },
    "summarize": {
      "version": "1.0.0",
      "installedAt": 1773037738157
    },
    "find-skills": {
      "version": "0.1.0",
      "installedAt": 1773037741271
    },
    "self-improving-agent": {
      "version": "3.0.0",
      "installedAt": 1773086407550
    }
  }
}
